README.rst
setup.py
pysimstrat/SimstratOutput.py
pysimstrat/__init__.py
pysimstrat/configuration.py
pysimstrat/date.py
pysimstrat/pest.py
pysimstrat/swissmetnet.py
pysimstrat.egg-info/PKG-INFO
pysimstrat.egg-info/SOURCES.txt
pysimstrat.egg-info/dependency_links.txt
pysimstrat.egg-info/not-zip-safe
pysimstrat.egg-info/requires.txt
pysimstrat.egg-info/top_level.txt